{"cameraMode":{"drawMode":0,"name":"Shaded","section":"Shading Mode"},"sceneLighting":true,"audioPlay":false,"sceneViewState":{"m_AlwaysRefresh":false,"showFog":true,"showSkybox":true,"showFlares":true,"showImageEffects":true,"showParticleSystems":true,"showVisualEffectGraphs":true,"m_FxEnabled":true},"in2DMode":false,"pivot":{"x":440.1675109863281,"y":260.2710876464844,"z":1.29217529296875},"rotation":{"x":0.022494476288557054,"y":0.017994476482272149,"z":-0.00040494423592463136,"w":0.9995850920677185},"size":450.1869812011719,"orthographic":false}